dtbase/__init__.py
dtbase/config.py
dtbase/engine.py
dtbase-0.0.5.dist-info/WHEEL
dtbase-0.0.5.dist-info/METADATA
dtbase-0.0.5.dist-info/RECORD
